scanoramaCT/__init__.py
scanoramaCT/scanoramaCT.py
scanoramaCT/utils.py
scanoramaCT-1.2.0.dist-info/LICENSE
scanoramaCT-1.2.0.dist-info/METADATA
scanoramaCT-1.2.0.dist-info/WHEEL
scanoramaCT-1.2.0.dist-info/top_level.txt
scanoramaCT-1.2.0.dist-info/RECORD
