Metadata-Version: 2.1
Name: scanoramaCT
Version: 1.2.0
Summary: An adapted version of the Scanorama package by Brian Hie, Bryan Bryson, and Bonnie Berger for application to CytoTRACE.
Home-page: UNKNOWN
Author: Gunsagar Gulati
Author-email: gunsagargulati@gmail.com
License: UNKNOWN
Platform: UNKNOWN
Classifier: Programming Language :: Python :: 3
Classifier: License :: OSI Approved :: MIT License
Classifier: Operating System :: OS Independent
Requires-Dist: annoy (>=1.11.5)
Requires-Dist: fbpca (>=1.0)
Requires-Dist: geosketch (>=1.0)
Requires-Dist: intervaltree (==2.1.0)
Requires-Dist: matplotlib (>=2.0.2)
Requires-Dist: numpy (>=1.12.0)
Requires-Dist: scipy (>=1.0.0)
Requires-Dist: scikit-learn (>=0.20rc1)
